langchain_sambanova/__init__.py
langchain_sambanova/chat_models.py
langchain_sambanova/embeddings.py
langchain_sambanova/py.typed
langchain_sambanova/version.py
langchain_sambanova-1.0.0.dist-info/METADATA
langchain_sambanova-1.0.0.dist-info/WHEEL
langchain_sambanova-1.0.0.dist-info/licenses/LICENSE
langchain_sambanova-1.0.0.dist-info/RECORD
