Metadata-Version: 2.4
Name: langchain-sambanova
Version: 1.0.0
Summary: An integration package connecting SambaNova and LangChain
License: MIT
License-File: LICENSE
Author: SambaNova Systems
Requires-Python: >=3.10.0,<4.0
Classifier: License :: OSI Approved :: MIT License
Classifier: Programming Language :: Python :: 3
Classifier: Programming Language :: Python :: 3.10
Classifier: Programming Language :: Python :: 3.11
Classifier: Programming Language :: Python :: 3.12
Classifier: Programming Language :: Python :: 3.13
Classifier: Programming Language :: Python :: 3.14
Requires-Dist: langchain-core (>0.3.0,<2.0.0)
Requires-Dist: sambanova (>=1.1.3,<2.0.0)
Requires-Dist: types-requests
Project-URL: Repository, https://github.com/sambanova/langchain-sambanova
Project-URL: Release Notes, https://github.com/sambanova/langchain-sambanova/releases
Project-URL: Source Code, https://github.com/sambanova/langchain-sambanova
